tests/__init__.py
tests/conftest.py
tests/test_comm.py
tests/test_config.py
tests/test_dateutils.py
tests/test_dlso.py
tests/test_fileutils.py
tests/test_htmlutils.py
tests/test_imageutils.py
tests/test_logger.py
tests/test_mp.py
tests/test_mt.py
tests/test_network.py
tests/test_reutils.py
tests/test_sysutils.py
tests/test_textutils.py
tests/test_urlutils.py
tests/test_zwtask.py
tests/test_zwtask2.py
zwutils/__init__.py
zwutils/__version__.py
zwutils/comm.py
zwutils/config.py
zwutils/dateutils.py
zwutils/dlso.py
zwutils/encode.py
zwutils/fileutils.py
zwutils/geoutils.py
zwutils/htmlutils.py
zwutils/httputils.py
zwutils/imageutils.py
zwutils/logger.py
zwutils/logging.py
zwutils/mprocessing.py
zwutils/mthreading.py
zwutils/network.py
zwutils/rand.py
zwutils/reutils.py
zwutils/sysutils.py
zwutils/textutils.py
zwutils/urlutils.py
zwutils/zwtask.py
zwutils-0.2.7.dist-info/LICENSE
zwutils-0.2.7.dist-info/METADATA
zwutils-0.2.7.dist-info/WHEEL
zwutils-0.2.7.dist-info/top_level.txt
zwutils-0.2.7.dist-info/RECORD
