Metadata-Version: 2.1
Name: zwutils
Version: 0.2.7
Summary: Personal Python Utilities
Home-page: https://github.com/njzhaowei/zwutils
Author: Zhao Wei
Author-email: yewberry@163.com
License: Apache 2.0
Platform: all
Classifier: Programming Language :: Python :: 3
Classifier: License :: OSI Approved :: Apache Software License
Classifier: Operating System :: OS Independent
Requires-Python: >=3.6
License-File: LICENSE
Requires-Dist: requests
Requires-Dist: chardet
Requires-Dist: psutil
Requires-Dist: python-dateutil
Requires-Dist: beautifulsoup4
Requires-Dist: lxml
Requires-Dist: pillow
